{
  "id": "ClaraEmailIngest",
  "name": "Clara — Email Ingestion",
  "active": true,
  "settings": { "executionOrder": "v1", "errorWorkflow": "ClaraErrorHandlr" },
  "nodes": [
    {
      "id": "node-gmail-trigger",
      "name": "Gmail Trigger",
      "type": "n8n-nodes-base.gmailTrigger",
      "typeVersion": 1.2,
      "position": [0, 0],
      "parameters": {
        "pollTimes": { "item": [{ "mode": "everyMinute" }] },
        "simple": false,
        "filters": { "q": "has:attachment", "readStatus": "unread" },
        "options": { "downloadAttachments": true }
      },
      "credentials": {
        "gmailOAuth2": {
          "id": "ClaraGmailOAuth2",
          "name": "Clara Gmail"
        }
      }
    },
    {
      "id": "node-expand-attachments",
      "name": "Expand attachments",
      "type": "n8n-nodes-base.code",
      "typeVersion": 2,
      "position": [224, 0],
      "parameters": {
        "jsCode": "// One email can carry several attachments; fan out to one item per\n// usable document. Policy (allowlist, dedup) is NOT decided here — the\n// app owns that; this node only reshapes data.\n//\n// IMPORTANT: attachment bytes are fetched via getBinaryDataBuffer, never\n// read from item.binary[key].data directly — depending on n8n's binary\n// storage mode, .data can be a reference stub instead of real base64.\nconst ALLOWED = new Set(['application/pdf', 'image/png', 'image/jpeg', 'image/webp']);\nconst out = [];\nconst items = $input.all();\nfor (let i = 0; i < items.length; i++) {\n  const item = items[i];\n  const sender =\n    item.json.from?.value?.[0]?.address ??\n    String(item.json.from ?? '').match(/[\\w.+-]+@[\\w-]+\\.[\\w.-]+/)?.[0] ??\n    null;\n  if (!sender) continue;\n  const subject = item.json.subject ?? '(no subject)';\n  const messageId = item.json.id;\n  for (const key of Object.keys(item.binary ?? {})) {\n    const att = item.binary[key];\n    if (!ALLOWED.has(att.mimeType)) continue;\n    const buffer = await this.helpers.getBinaryDataBuffer(i, key);\n    out.push({\n      json: {\n        fileName: att.fileName ?? `${key}`,\n        mimeType: att.mimeType,\n        data: buffer.toString('base64'),\n        sender,\n        subject,\n        messageId\n      }\n    });\n  }\n}\nreturn out; // empty array = nothing to do, execution ends quietly"
      }
    },
    {
      "id": "node-deliver-to-app",
      "name": "Deliver to app",
      "type": "n8n-nodes-base.httpRequest",
      "typeVersion": 4.2,
      "position": [448, 0],
      "retryOnFail": true,
      "maxTries": 3,
      "waitBetweenTries": 5000,
      "parameters": {
        "method": "POST",
        "url": "http://host.docker.internal:3000/api/internal/invoices/ingest",
        "authentication": "genericCredentialType",
        "genericAuthType": "httpHeaderAuth",
        "sendBody": true,
        "specifyBody": "json",
        "jsonBody": "={{ JSON.stringify($json) }}",
        "options": {}
      },
      "credentials": {
        "httpHeaderAuth": {
          "id": "ClaraInternalKey",
          "name": "Clara Internal API"
        }
      }
    },
    {
      "id": "77d6dd83-c704-4df3-8bde-2e6732ec054c",
      "name": "Mark a message as read",
      "type": "n8n-nodes-base.gmail",
      "typeVersion": 2.2,
      "position": [656, 0],
      "parameters": {
        "operation": "markAsRead",
        "messageId": "={{ $('Expand attachments').item.json.messageId }}"
      },
      "credentials": {
        "gmailOAuth2": {
          "id": "ClaraGmailOAuth2",
          "name": "Clara Gmail"
        }
      }
    }
  ],
  "connections": {
    "Gmail Trigger": {
      "main": [
        [{ "node": "Expand attachments", "type": "main", "index": 0 }]
      ]
    },
    "Expand attachments": {
      "main": [
        [{ "node": "Deliver to app", "type": "main", "index": 0 }]
      ]
    },
    "Deliver to app": {
      "main": [
        [{ "node": "Mark a message as read", "type": "main", "index": 0 }]
      ]
    }
  }
}
